jblack/__init__.py
jblack/arguments.json
jblack/cli.py
jblack/jblack
jblack/useful.py
jblack/worker.py
jblack-1.2.data/scripts/jblack
jblack-1.2.dist-info/METADATA
jblack-1.2.dist-info/WHEEL
jblack-1.2.dist-info/top_level.txt
jblack-1.2.dist-info/RECORD
