Metadata-Version: 2.1
Name: jblack
Version: 1.2
Summary: Apply black on your jupyter notebook.
Home-page: https://github.com/jupyter-black/jblack
Author: QuentinN42
Author-email: jupyter.black@gmail.com
License: UNKNOWN
Platform: UNKNOWN
Classifier: Programming Language :: Python :: 3
Classifier: License :: OSI Approved :: GNU General Public License v3 (GPLv3)
Classifier: Operating System :: OS Independent
Requires-Python: >=3.6
